dayonewriter/__init__.py
dayonewriter/dayonewriter.py
dayonewriter/entry.py
dayonewriter/helper.py
dayonewriter/markdown.py
dayonewriter-1.0.dist-info/LICENSE
dayonewriter-1.0.dist-info/METADATA
dayonewriter-1.0.dist-info/WHEEL
dayonewriter-1.0.dist-info/top_level.txt
dayonewriter-1.0.dist-info/RECORD
