Metadata-Version: 2.1
Name: dayonewriter
Version: 1.0
Summary: Python wrapper which internally uses dayone-cli. Compatible with Day One 2+.
Home-page: https://github.com/ankschoubey/dayonewriter
Author: Ankush Choubey
Author-email: ankushchoubey@outlook.com
License: UNKNOWN
Platform: UNKNOWN
Classifier: Programming Language :: Python :: 3
Classifier: License :: OSI Approved :: MIT License
Classifier: Operating System :: OS Independent
